onnx_hameln/__init__.py
onnx_hameln/core/__init__.py
onnx_hameln/core/hameln.py
onnx_hameln/core/pattern.py
onnx_hameln/core/rewriter/__init__.py
onnx_hameln/core/rewriter/conv_conv_concat_bn_leakyrelu_rewriter.py
onnx_hameln-0.0.3.dist-info/LICENSE
onnx_hameln-0.0.3.dist-info/METADATA
onnx_hameln-0.0.3.dist-info/WHEEL
onnx_hameln-0.0.3.dist-info/top_level.txt
onnx_hameln-0.0.3.dist-info/RECORD
