Metadata-Version: 2.1
Name: onnx-hameln
Version: 0.0.3
Summary: an onnx rewrite tool
Home-page: https://github.com/irasin/onnx_hameln
Author: irasin
Author-email: edad811@gmail.com
License: Apache License 2.0
Platform: UNKNOWN
Requires-Python: >=3.6
Requires-Dist: networkx
Requires-Dist: numpy
Requires-Dist: onnx
Requires-Dist: onnxoptimizer
